{
  "project_info": {
    "project_number": "503008586073",
    "project_id": "prueba-android-4de49",
    "storage_bucket": "prueba-android-4de49.appspot.com"
  },
  "client": [
    {
      "client_info": {
        "mobilesdk_app_id": "1:503008586073:android:036edb443166b4f2d80448",
        "android_client_info": {
          "package_name": "com.proyectoandroid.pruebafirebase"
        }
      },
      "oauth_client": [],
      "api_key": [
        {
          "current_key": "AIzaSyDmmOv-XOXg8dpy-jotFM-amgkJyxjltkM"
        }
      ],
      "services": {
        "appinvite_service": {
          "other_platform_oauth_client": []
        }
      }
    }
  ],
  "configuration_version": "1"
}